src/__init__.py
src/mousejiggler.py
mousejiggler-0.1.0.dist-info/METADATA
mousejiggler-0.1.0.dist-info/WHEEL
mousejiggler-0.1.0.dist-info/top_level.txt
mousejiggler-0.1.0.dist-info/RECORD
