Metadata-Version: 2.1
Name: mousejiggler
Version: 0.1.0
Summary: A package to keep your cat AND screensaver busy.
Home-page: https://github.com/idrisschebak/mousejiggler
Author: Idriss CHEBAK
Author-email: idrisschebak@me.com
Requires-Python: >=3.6
Requires-Dist: Pillow
